{"0NEjJxtHRkA_0": {"annotations": {"label": "together", "segment": [344.16, 349.16]}, "annotations_frame": {"label": "together", "segment": [8604.0, 8729.0]}, "annotations_rounded": {"label": "together", "segment": [344.0, 350.0]}, "duration": 5.0, "duration_frame": 125.0, "duration_rounded": 6.0, "subset": "train", "url": "https://www.youtube.com/watch?v=0NEjJxtHRkA"}, "0NEjJxtHRkA_1": {"annotations": {"label": "together", "segment": [388.12, 393.12]}, "annotations_frame": {"label": "together", "segment": [9703.0, 9828.0]}, "annotations_rounded": {"label": "together", "segment": [388.0, 394.0]}, "duration": 5.0, "duration_frame": 125.0, "duration_rounded": 6.0, "subset": "train", "url": "https://www.youtube.com/watch?v=0NEjJxtHRkA"}, "0NEjJxtHRkA_2": {"annotations": {"label": "left", "segment": [592.32, 597.32]}, "annotations_frame": {"label": "left", "segment": [14808.0, 14933.0]}, "annotations_rounded": {"label": "left", "segment": [592.0, 598.0]}, "duration": 5.0, "duration_frame": 125.0, "duration_rounded": 6.0, "subset": "train", "url": "https://www.youtube.com/watch?v=0NEjJxtHRkA"}, "0NEjJxtHRkA_3": {"annotations": {"label": "together", "segment": [780.2, 785.2]}, "annotations_frame": {"label": "together", "segment": [19505.0, 19630.0]}, "annotations_rounded": {"label": "together", "segment": [780.0, 786.0]}, "duration": 5.0, "duration_frame": 125.0, "duration_rounded": 6.0, "subset": "train", "url": "https://www.youtube.com/watch?v=0NEjJxtHRkA"}, "0NEjJxtHRkA_4": {"annotations": {"label": "left", "segment": [825.4, 830.4]}, "annotations_frame": {"label": "left", "segment": [20635.0, 20760.0]}, "annotations_rounded": {"label": "left", "segment": [825.0, 831.0]}, "duration": 5.0, "duration_frame": 125.0, "duration_rounded": 6.0, "subset": "train", "url": "https://www.youtube.com/watch?v=0NEjJxtHRkA"}, "0NEjJxtHRkA_5": {"annotations": {"label": "left", "segment": [841.56, 846.56]}, "annotations_frame": {"label": "left", "segment": [21039.0, 21164.0]}, "annotations_rounded": {"label": "left", "segment": [841.0, 847.0]}, "duration": 5.0, "duration_frame": 125.0, "duration_rounded": 6.0, "subset": "train", "url": "https://www.youtube.com/watch?v=0NEjJxtHRkA"}, "0NEjJxtHRkA_6": {"annotations": {"label": "together", "segment": [870.2, 875.2]}, "annotations_frame": {"label": "together", "segment": [21755.0, 21880.0]}, "annotations_rounded": {"label": "together", "segment": [870.0, 876.0]}, "duration": 5.0, "duration_frame": 125.0, "duration_rounded": 6.0, "subset": "train", "url": "https://www.youtube.com/watch?v=0NEjJxtHRkA"}}