{"_Z_TDuuHPyY_0": {"annotations": {"label": "right", "segment": [102.44, 107.44]}, "annotations_frame": {"label": "right", "segment": [2561.0, 2686.0]}, "annotations_rounded": {"label": "right", "segment": [102.0, 108.0]}, "duration": 5.0, "duration_frame": 125.0, "duration_rounded": 6.0, "subset": "train", "url": "https://www.youtube.com/watch?v=_Z_TDuuHPyY"}, "_Z_TDuuHPyY_1": {"annotations": {"label": "left", "segment": [413.52, 418.52]}, "annotations_frame": {"label": "left", "segment": [10338.0, 10463.0]}, "annotations_rounded": {"label": "left", "segment": [413.0, 419.0]}, "duration": 5.0, "duration_frame": 125.0, "duration_rounded": 6.0, "subset": "train", "url": "https://www.youtube.com/watch?v=_Z_TDuuHPyY"}, "_Z_TDuuHPyY_2": {"annotations": {"label": "left", "segment": [490.04, 495.04]}, "annotations_frame": {"label": "left", "segment": [12251.0, 12376.0]}, "annotations_rounded": {"label": "left", "segment": [490.0, 496.0]}, "duration": 5.0, "duration_frame": 125.0, "duration_rounded": 6.0, "subset": "train", "url": "https://www.youtube.com/watch?v=_Z_TDuuHPyY"}, "_Z_TDuuHPyY_3": {"annotations": {"label": "left", "segment": [583.08, 588.08]}, "annotations_frame": {"label": "left", "segment": [14577.0, 14702.0]}, "annotations_rounded": {"label": "left", "segment": [583.0, 589.0]}, "duration": 5.0, "duration_frame": 125.0, "duration_rounded": 6.0, "subset": "train", "url": "https://www.youtube.com/watch?v=_Z_TDuuHPyY"}, "_Z_TDuuHPyY_4": {"annotations": {"label": "right", "segment": [745.56, 750.56]}, "annotations_frame": {"label": "right", "segment": [18639.0, 18764.0]}, "annotations_rounded": {"label": "right", "segment": [745.0, 751.0]}, "duration": 5.0, "duration_frame": 125.0, "duration_rounded": 6.0, "subset": "train", "url": "https://www.youtube.com/watch?v=_Z_TDuuHPyY"}, "_Z_TDuuHPyY_5": {"annotations": {"label": "left", "segment": [765.68, 770.68]}, "annotations_frame": {"label": "left", "segment": [19142.0, 19267.0]}, "annotations_rounded": {"label": "left", "segment": [765.0, 771.0]}, "duration": 5.0, "duration_frame": 125.0, "duration_rounded": 6.0, "subset": "train", "url": "https://www.youtube.com/watch?v=_Z_TDuuHPyY"}, "_Z_TDuuHPyY_6": {"annotations": {"label": "right", "segment": [875.92, 880.92]}, "annotations_frame": {"label": "right", "segment": [21898.0, 22023.0]}, "annotations_rounded": {"label": "right", "segment": [875.0, 881.0]}, "duration": 5.0, "duration_frame": 125.0, "duration_rounded": 6.0, "subset": "train", "url": "https://www.youtube.com/watch?v=_Z_TDuuHPyY"}, "_Z_TDuuHPyY_7": {"annotations": {"label": "right", "segment": [891.36, 896.36]}, "annotations_frame": {"label": "right", "segment": [22284.0, 22409.0]}, "annotations_rounded": {"label": "right", "segment": [891.0, 897.0]}, "duration": 5.0, "duration_frame": 125.0, "duration_rounded": 6.0, "subset": "train", "url": "https://www.youtube.com/watch?v=_Z_TDuuHPyY"}, "_Z_TDuuHPyY_8": {"annotations": {"label": "right", "segment": [910.32, 915.32]}, "annotations_frame": {"label": "right", "segment": [22758.0, 22883.0]}, "annotations_rounded": {"label": "right", "segment": [910.0, 916.0]}, "duration": 5.0, "duration_frame": 125.0, "duration_rounded": 6.0, "subset": "train", "url": "https://www.youtube.com/watch?v=_Z_TDuuHPyY"}, "_Z_TDuuHPyY_9": {"annotations": {"label": "together", "segment": [1047.12, 1052.12]}, "annotations_frame": {"label": "together", "segment": [26178.0, 26303.0]}, "annotations_rounded": {"label": "together", "segment": [1047.0, 1053.0]}, "duration": 5.0, "duration_frame": 125.0, "duration_rounded": 6.0, "subset": "train", "url": "https://www.youtube.com/watch?v=_Z_TDuuHPyY"}, "_Z_TDuuHPyY_10": {"annotations": {"label": "left", "segment": [1080.28, 1085.28]}, "annotations_frame": {"label": "left", "segment": [27007.0, 27132.0]}, "annotations_rounded": {"label": "left", "segment": [1080.0, 1086.0]}, "duration": 5.0, "duration_frame": 125.0, "duration_rounded": 6.0, "subset": "train", "url": "https://www.youtube.com/watch?v=_Z_TDuuHPyY"}}