{"cEhhDllQUj8_0": {"annotations": {"label": "together", "segment": [376.52, 381.52]}, "annotations_frame": {"label": "together", "segment": [9413.0, 9538.0]}, "annotations_rounded": {"label": "together", "segment": [376.0, 382.0]}, "duration": 5.0, "duration_frame": 125.0, "duration_rounded": 6.0, "subset": "train", "url": "https://www.youtube.com/watch?v=cEhhDllQUj8"}, "cEhhDllQUj8_1": {"annotations": {"label": "left", "segment": [408.44, 413.44]}, "annotations_frame": {"label": "left", "segment": [10211.0, 10336.0]}, "annotations_rounded": {"label": "left", "segment": [408.0, 414.0]}, "duration": 5.0, "duration_frame": 125.0, "duration_rounded": 6.0, "subset": "train", "url": "https://www.youtube.com/watch?v=cEhhDllQUj8"}, "cEhhDllQUj8_2": {"annotations": {"label": "right", "segment": [450.32, 455.32]}, "annotations_frame": {"label": "right", "segment": [11258.0, 11383.0]}, "annotations_rounded": {"label": "right", "segment": [450.0, 456.0]}, "duration": 5.0, "duration_frame": 125.0, "duration_rounded": 6.0, "subset": "train", "url": "https://www.youtube.com/watch?v=cEhhDllQUj8"}, "cEhhDllQUj8_3": {"annotations": {"label": "together", "segment": [501.52, 506.52]}, "annotations_frame": {"label": "together", "segment": [12538.0, 12663.0]}, "annotations_rounded": {"label": "together", "segment": [501.0, 507.0]}, "duration": 5.0, "duration_frame": 125.0, "duration_rounded": 6.0, "subset": "train", "url": "https://www.youtube.com/watch?v=cEhhDllQUj8"}, "cEhhDllQUj8_4": {"annotations": {"label": "together", "segment": [511.76, 516.76]}, "annotations_frame": {"label": "together", "segment": [12794.0, 12919.0]}, "annotations_rounded": {"label": "together", "segment": [511.0, 517.0]}, "duration": 5.0, "duration_frame": 125.0, "duration_rounded": 6.0, "subset": "train", "url": "https://www.youtube.com/watch?v=cEhhDllQUj8"}, "cEhhDllQUj8_5": {"annotations": {"label": "together", "segment": [578.48, 583.48]}, "annotations_frame": {"label": "together", "segment": [14462.0, 14587.0]}, "annotations_rounded": {"label": "together", "segment": [578.0, 584.0]}, "duration": 5.0, "duration_frame": 125.0, "duration_rounded": 6.0, "subset": "train", "url": "https://www.youtube.com/watch?v=cEhhDllQUj8"}, "cEhhDllQUj8_6": {"annotations": {"label": "right", "segment": [658.48, 663.48]}, "annotations_frame": {"label": "right", "segment": [16462.0, 16587.0]}, "annotations_rounded": {"label": "right", "segment": [658.0, 664.0]}, "duration": 5.0, "duration_frame": 125.0, "duration_rounded": 6.0, "subset": "train", "url": "https://www.youtube.com/watch?v=cEhhDllQUj8"}, "cEhhDllQUj8_7": {"annotations": {"label": "right", "segment": [670.72, 675.72]}, "annotations_frame": {"label": "right", "segment": [16768.0, 16893.0]}, "annotations_rounded": {"label": "right", "segment": [670.0, 676.0]}, "duration": 5.0, "duration_frame": 125.0, "duration_rounded": 6.0, "subset": "train", "url": "https://www.youtube.com/watch?v=cEhhDllQUj8"}}