{"COWLSUVjq64_0": {"annotations": {"label": "right", "segment": [179.12, 184.12]}, "annotations_frame": {"label": "right", "segment": [4478.0, 4603.0]}, "annotations_rounded": {"label": "right", "segment": [179.0, 185.0]}, "duration": 5.0, "duration_frame": 125.0, "duration_rounded": 6.0, "subset": "train", "url": "https://www.youtube.com/watch?v=COWLSUVjq64"}, "COWLSUVjq64_1": {"annotations": {"label": "left", "segment": [330.04, 335.04]}, "annotations_frame": {"label": "left", "segment": [8251.0, 8376.0]}, "annotations_rounded": {"label": "left", "segment": [330.0, 336.0]}, "duration": 5.0, "duration_frame": 125.0, "duration_rounded": 6.0, "subset": "train", "url": "https://www.youtube.com/watch?v=COWLSUVjq64"}, "COWLSUVjq64_2": {"annotations": {"label": "together", "segment": [509.0, 514.0]}, "annotations_frame": {"label": "together", "segment": [12725.0, 12850.0]}, "annotations_rounded": {"label": "together", "segment": [509.0, 514.0]}, "duration": 5.0, "duration_frame": 125.0, "duration_rounded": 5.0, "subset": "train", "url": "https://www.youtube.com/watch?v=COWLSUVjq64"}, "COWLSUVjq64_3": {"annotations": {"label": "left", "segment": [695.56, 700.56]}, "annotations_frame": {"label": "left", "segment": [17389.0, 17514.0]}, "annotations_rounded": {"label": "left", "segment": [695.0, 701.0]}, "duration": 5.0, "duration_frame": 125.0, "duration_rounded": 6.0, "subset": "train", "url": "https://www.youtube.com/watch?v=COWLSUVjq64"}, "COWLSUVjq64_4": {"annotations": {"label": "right", "segment": [816.28, 821.28]}, "annotations_frame": {"label": "right", "segment": [20407.0, 20532.0]}, "annotations_rounded": {"label": "right", "segment": [816.0, 822.0]}, "duration": 5.0, "duration_frame": 125.0, "duration_rounded": 6.0, "subset": "train", "url": "https://www.youtube.com/watch?v=COWLSUVjq64"}, "COWLSUVjq64_5": {"annotations": {"label": "right", "segment": [905.32, 910.32]}, "annotations_frame": {"label": "right", "segment": [22633.0, 22758.0]}, "annotations_rounded": {"label": "right", "segment": [905.0, 911.0]}, "duration": 5.0, "duration_frame": 125.0, "duration_rounded": 6.0, "subset": "train", "url": "https://www.youtube.com/watch?v=COWLSUVjq64"}, "COWLSUVjq64_6": {"annotations": {"label": "together", "segment": [1059.32, 1064.32]}, "annotations_frame": {"label": "together", "segment": [26483.0, 26608.0]}, "annotations_rounded": {"label": "together", "segment": [1059.0, 1065.0]}, "duration": 5.0, "duration_frame": 125.0, "duration_rounded": 6.0, "subset": "train", "url": "https://www.youtube.com/watch?v=COWLSUVjq64"}, "COWLSUVjq64_7": {"annotations": {"label": "right", "segment": [1110.2, 1115.2]}, "annotations_frame": {"label": "right", "segment": [27755.0, 27880.0]}, "annotations_rounded": {"label": "right", "segment": [1110.0, 1116.0]}, "duration": 5.0, "duration_frame": 125.0, "duration_rounded": 6.0, "subset": "train", "url": "https://www.youtube.com/watch?v=COWLSUVjq64"}, "COWLSUVjq64_8": {"annotations": {"label": "right", "segment": [1128.32, 1133.32]}, "annotations_frame": {"label": "right", "segment": [28208.0, 28333.0]}, "annotations_rounded": {"label": "right", "segment": [1128.0, 1134.0]}, "duration": 5.0, "duration_frame": 125.0, "duration_rounded": 6.0, "subset": "train", "url": "https://www.youtube.com/watch?v=COWLSUVjq64"}, "COWLSUVjq64_9": {"annotations": {"label": "together", "segment": [1277.24, 1282.24]}, "annotations_frame": {"label": "together", "segment": [31931.0, 32056.0]}, "annotations_rounded": {"label": "together", "segment": [1277.0, 1283.0]}, "duration": 5.0, "duration_frame": 125.0, "duration_rounded": 6.0, "subset": "train", "url": "https://www.youtube.com/watch?v=COWLSUVjq64"}, "COWLSUVjq64_10": {"annotations": {"label": "right", "segment": [1310.64, 1315.64]}, "annotations_frame": {"label": "right", "segment": [32766.0, 32891.0]}, "annotations_rounded": {"label": "right", "segment": [1310.0, 1316.0]}, "duration": 5.0, "duration_frame": 125.0, "duration_rounded": 6.0, "subset": "train", "url": "https://www.youtube.com/watch?v=COWLSUVjq64"}, "COWLSUVjq64_11": {"annotations": {"label": "left", "segment": [1539.04, 1544.04]}, "annotations_frame": {"label": "left", "segment": [38476.0, 38601.0]}, "annotations_rounded": {"label": "left", "segment": [1539.0, 1545.0]}, "duration": 5.0, "duration_frame": 125.0, "duration_rounded": 6.0, "subset": "train", "url": "https://www.youtube.com/watch?v=COWLSUVjq64"}, "COWLSUVjq64_12": {"annotations": {"label": "together", "segment": [1621.6, 1626.6]}, "annotations_frame": {"label": "together", "segment": [40540.0, 40665.0]}, "annotations_rounded": {"label": "together", "segment": [1621.0, 1627.0]}, "duration": 5.0, "duration_frame": 125.0, "duration_rounded": 6.0, "subset": "train", "url": "https://www.youtube.com/watch?v=COWLSUVjq64"}}