{"DdJryW9Utos_0": {"annotations": {"label": "right", "segment": [100.48, 105.48]}, "annotations_frame": {"label": "right", "segment": [2512.0, 2637.0]}, "annotations_rounded": {"label": "right", "segment": [100.0, 106.0]}, "duration": 5.0, "duration_frame": 125.0, "duration_rounded": 6.0, "subset": "train", "url": "https://www.youtube.com/watch?v=DdJryW9Utos"}, "DdJryW9Utos_1": {"annotations": {"label": "together", "segment": [165.04, 170.04]}, "annotations_frame": {"label": "together", "segment": [4126.0, 4251.0]}, "annotations_rounded": {"label": "together", "segment": [165.0, 171.0]}, "duration": 5.0, "duration_frame": 125.0, "duration_rounded": 6.0, "subset": "train", "url": "https://www.youtube.com/watch?v=DdJryW9Utos"}, "DdJryW9Utos_2": {"annotations": {"label": "right", "segment": [280.4, 285.4]}, "annotations_frame": {"label": "right", "segment": [7010.0, 7135.0]}, "annotations_rounded": {"label": "right", "segment": [280.0, 286.0]}, "duration": 5.0, "duration_frame": 125.0, "duration_rounded": 6.0, "subset": "train", "url": "https://www.youtube.com/watch?v=DdJryW9Utos"}, "DdJryW9Utos_3": {"annotations": {"label": "together", "segment": [559.4, 564.4]}, "annotations_frame": {"label": "together", "segment": [13985.0, 14110.0]}, "annotations_rounded": {"label": "together", "segment": [559.0, 565.0]}, "duration": 5.0, "duration_frame": 125.0, "duration_rounded": 6.0, "subset": "train", "url": "https://www.youtube.com/watch?v=DdJryW9Utos"}, "DdJryW9Utos_4": {"annotations": {"label": "left", "segment": [752.64, 757.64]}, "annotations_frame": {"label": "left", "segment": [18816.0, 18941.0]}, "annotations_rounded": {"label": "left", "segment": [752.0, 758.0]}, "duration": 5.0, "duration_frame": 125.0, "duration_rounded": 6.0, "subset": "train", "url": "https://www.youtube.com/watch?v=DdJryW9Utos"}}