{"gY0QhwLHPjk_0": {"annotations": {"label": "right", "segment": [115.2, 120.2]}, "annotations_frame": {"label": "right", "segment": [2880.0, 3005.0]}, "annotations_rounded": {"label": "right", "segment": [115.0, 121.0]}, "duration": 5.0, "duration_frame": 125.0, "duration_rounded": 6.0, "subset": "train", "url": "https://www.youtube.com/watch?v=gY0QhwLHPjk"}, "gY0QhwLHPjk_1": {"annotations": {"label": "left", "segment": [189.0, 194.0]}, "annotations_frame": {"label": "left", "segment": [4725.0, 4850.0]}, "annotations_rounded": {"label": "left", "segment": [189.0, 194.0]}, "duration": 5.0, "duration_frame": 125.0, "duration_rounded": 5.0, "subset": "train", "url": "https://www.youtube.com/watch?v=gY0QhwLHPjk"}, "gY0QhwLHPjk_2": {"annotations": {"label": "left", "segment": [204.6, 209.6]}, "annotations_frame": {"label": "left", "segment": [5115.0, 5240.0]}, "annotations_rounded": {"label": "left", "segment": [204.0, 210.0]}, "duration": 5.0, "duration_frame": 125.0, "duration_rounded": 6.0, "subset": "train", "url": "https://www.youtube.com/watch?v=gY0QhwLHPjk"}, "gY0QhwLHPjk_3": {"annotations": {"label": "together", "segment": [340.04, 345.04]}, "annotations_frame": {"label": "together", "segment": [8501.0, 8626.0]}, "annotations_rounded": {"label": "together", "segment": [340.0, 346.0]}, "duration": 5.0, "duration_frame": 125.0, "duration_rounded": 6.0, "subset": "train", "url": "https://www.youtube.com/watch?v=gY0QhwLHPjk"}, "gY0QhwLHPjk_4": {"annotations": {"label": "left", "segment": [421.68, 426.68]}, "annotations_frame": {"label": "left", "segment": [10542.0, 10667.0]}, "annotations_rounded": {"label": "left", "segment": [421.0, 427.0]}, "duration": 5.0, "duration_frame": 125.0, "duration_rounded": 6.0, "subset": "train", "url": "https://www.youtube.com/watch?v=gY0QhwLHPjk"}, "gY0QhwLHPjk_5": {"annotations": {"label": "left", "segment": [431.8, 436.8]}, "annotations_frame": {"label": "left", "segment": [10795.0, 10920.0]}, "annotations_rounded": {"label": "left", "segment": [431.0, 437.0]}, "duration": 5.0, "duration_frame": 125.0, "duration_rounded": 6.0, "subset": "train", "url": "https://www.youtube.com/watch?v=gY0QhwLHPjk"}, "gY0QhwLHPjk_6": {"annotations": {"label": "right", "segment": [510.4, 515.4]}, "annotations_frame": {"label": "right", "segment": [12760.0, 12885.0]}, "annotations_rounded": {"label": "right", "segment": [510.0, 516.0]}, "duration": 5.0, "duration_frame": 125.0, "duration_rounded": 6.0, "subset": "train", "url": "https://www.youtube.com/watch?v=gY0QhwLHPjk"}, "gY0QhwLHPjk_7": {"annotations": {"label": "right", "segment": [569.44, 574.44]}, "annotations_frame": {"label": "right", "segment": [14236.0, 14361.0]}, "annotations_rounded": {"label": "right", "segment": [569.0, 575.0]}, "duration": 5.0, "duration_frame": 125.0, "duration_rounded": 6.0, "subset": "train", "url": "https://www.youtube.com/watch?v=gY0QhwLHPjk"}, "gY0QhwLHPjk_8": {"annotations": {"label": "together", "segment": [734.24, 739.24]}, "annotations_frame": {"label": "together", "segment": [18356.0, 18481.0]}, "annotations_rounded": {"label": "together", "segment": [734.0, 740.0]}, "duration": 5.0, "duration_frame": 125.0, "duration_rounded": 6.0, "subset": "train", "url": "https://www.youtube.com/watch?v=gY0QhwLHPjk"}, "gY0QhwLHPjk_9": {"annotations": {"label": "right", "segment": [754.04, 759.04]}, "annotations_frame": {"label": "right", "segment": [18851.0, 18976.0]}, "annotations_rounded": {"label": "right", "segment": [754.0, 760.0]}, "duration": 5.0, "duration_frame": 125.0, "duration_rounded": 6.0, "subset": "train", "url": "https://www.youtube.com/watch?v=gY0QhwLHPjk"}, "gY0QhwLHPjk_10": {"annotations": {"label": "right", "segment": [908.64, 913.64]}, "annotations_frame": {"label": "right", "segment": [22716.0, 22841.0]}, "annotations_rounded": {"label": "right", "segment": [908.0, 914.0]}, "duration": 5.0, "duration_frame": 125.0, "duration_rounded": 6.0, "subset": "train", "url": "https://www.youtube.com/watch?v=gY0QhwLHPjk"}}