{"HipQy1TNHSE_0": {"annotations": {"label": "together", "segment": [340.72, 345.72]}, "annotations_frame": {"label": "together", "segment": [8518.0, 8643.0]}, "annotations_rounded": {"label": "together", "segment": [340.0, 346.0]}, "duration": 5.0, "duration_frame": 125.0, "duration_rounded": 6.0, "subset": "train", "url": "https://www.youtube.com/watch?v=HipQy1TNHSE"}, "HipQy1TNHSE_1": {"annotations": {"label": "together", "segment": [590.24, 595.24]}, "annotations_frame": {"label": "together", "segment": [14756.0, 14881.0]}, "annotations_rounded": {"label": "together", "segment": [590.0, 596.0]}, "duration": 5.0, "duration_frame": 125.0, "duration_rounded": 6.0, "subset": "train", "url": "https://www.youtube.com/watch?v=HipQy1TNHSE"}, "HipQy1TNHSE_2": {"annotations": {"label": "right", "segment": [781.68, 786.68]}, "annotations_frame": {"label": "right", "segment": [19542.0, 19667.0]}, "annotations_rounded": {"label": "right", "segment": [781.0, 787.0]}, "duration": 5.0, "duration_frame": 125.0, "duration_rounded": 6.0, "subset": "train", "url": "https://www.youtube.com/watch?v=HipQy1TNHSE"}, "HipQy1TNHSE_3": {"annotations": {"label": "right", "segment": [883.72, 888.72]}, "annotations_frame": {"label": "right", "segment": [22093.0, 22218.0]}, "annotations_rounded": {"label": "right", "segment": [883.0, 889.0]}, "duration": 5.0, "duration_frame": 125.0, "duration_rounded": 6.0, "subset": "train", "url": "https://www.youtube.com/watch?v=HipQy1TNHSE"}, "HipQy1TNHSE_4": {"annotations": {"label": "together", "segment": [1037.92, 1042.92]}, "annotations_frame": {"label": "together", "segment": [25948.0, 26073.0]}, "annotations_rounded": {"label": "together", "segment": [1037.0, 1043.0]}, "duration": 5.0, "duration_frame": 125.0, "duration_rounded": 6.0, "subset": "train", "url": "https://www.youtube.com/watch?v=HipQy1TNHSE"}, "HipQy1TNHSE_5": {"annotations": {"label": "together", "segment": [1170.92, 1175.92]}, "annotations_frame": {"label": "together", "segment": [29273.0, 29398.0]}, "annotations_rounded": {"label": "together", "segment": [1170.0, 1176.0]}, "duration": 5.0, "duration_frame": 125.0, "duration_rounded": 6.0, "subset": "train", "url": "https://www.youtube.com/watch?v=HipQy1TNHSE"}}