{"hIQ8vcu01Ws_0": {"annotations": {"label": "right", "segment": [366.84, 371.84]}, "annotations_frame": {"label": "right", "segment": [9171.0, 9296.0]}, "annotations_rounded": {"label": "right", "segment": [366.0, 372.0]}, "duration": 5.0, "duration_frame": 125.0, "duration_rounded": 6.0, "subset": "train", "url": "https://www.youtube.com/watch?v=hIQ8vcu01Ws"}, "hIQ8vcu01Ws_1": {"annotations": {"label": "together", "segment": [410.4, 415.4]}, "annotations_frame": {"label": "together", "segment": [10260.0, 10385.0]}, "annotations_rounded": {"label": "together", "segment": [410.0, 416.0]}, "duration": 5.0, "duration_frame": 125.0, "duration_rounded": 6.0, "subset": "train", "url": "https://www.youtube.com/watch?v=hIQ8vcu01Ws"}, "hIQ8vcu01Ws_2": {"annotations": {"label": "right", "segment": [427.84, 432.84]}, "annotations_frame": {"label": "right", "segment": [10696.0, 10821.0]}, "annotations_rounded": {"label": "right", "segment": [427.0, 433.0]}, "duration": 5.0, "duration_frame": 125.0, "duration_rounded": 6.0, "subset": "train", "url": "https://www.youtube.com/watch?v=hIQ8vcu01Ws"}, "hIQ8vcu01Ws_3": {"annotations": {"label": "right", "segment": [442.2, 447.2]}, "annotations_frame": {"label": "right", "segment": [11055.0, 11180.0]}, "annotations_rounded": {"label": "right", "segment": [442.0, 448.0]}, "duration": 5.0, "duration_frame": 125.0, "duration_rounded": 6.0, "subset": "train", "url": "https://www.youtube.com/watch?v=hIQ8vcu01Ws"}, "hIQ8vcu01Ws_4": {"annotations": {"label": "left", "segment": [483.56, 488.56]}, "annotations_frame": {"label": "left", "segment": [12089.0, 12214.0]}, "annotations_rounded": {"label": "left", "segment": [483.0, 489.0]}, "duration": 5.0, "duration_frame": 125.0, "duration_rounded": 6.0, "subset": "train", "url": "https://www.youtube.com/watch?v=hIQ8vcu01Ws"}, "hIQ8vcu01Ws_5": {"annotations": {"label": "together", "segment": [535.92, 540.92]}, "annotations_frame": {"label": "together", "segment": [13398.0, 13523.0]}, "annotations_rounded": {"label": "together", "segment": [535.0, 541.0]}, "duration": 5.0, "duration_frame": 125.0, "duration_rounded": 6.0, "subset": "train", "url": "https://www.youtube.com/watch?v=hIQ8vcu01Ws"}, "hIQ8vcu01Ws_6": {"annotations": {"label": "right", "segment": [576.88, 581.88]}, "annotations_frame": {"label": "right", "segment": [14422.0, 14547.0]}, "annotations_rounded": {"label": "right", "segment": [576.0, 582.0]}, "duration": 5.0, "duration_frame": 125.0, "duration_rounded": 6.0, "subset": "train", "url": "https://www.youtube.com/watch?v=hIQ8vcu01Ws"}, "hIQ8vcu01Ws_7": {"annotations": {"label": "left", "segment": [690.24, 695.24]}, "annotations_frame": {"label": "left", "segment": [17256.0, 17381.0]}, "annotations_rounded": {"label": "left", "segment": [690.0, 696.0]}, "duration": 5.0, "duration_frame": 125.0, "duration_rounded": 6.0, "subset": "train", "url": "https://www.youtube.com/watch?v=hIQ8vcu01Ws"}, "hIQ8vcu01Ws_8": {"annotations": {"label": "left", "segment": [824.96, 829.96]}, "annotations_frame": {"label": "left", "segment": [20624.0, 20749.0]}, "annotations_rounded": {"label": "left", "segment": [824.0, 830.0]}, "duration": 5.0, "duration_frame": 125.0, "duration_rounded": 6.0, "subset": "train", "url": "https://www.youtube.com/watch?v=hIQ8vcu01Ws"}, "hIQ8vcu01Ws_9": {"annotations": {"label": "together", "segment": [909.96, 914.96]}, "annotations_frame": {"label": "together", "segment": [22749.0, 22874.0]}, "annotations_rounded": {"label": "together", "segment": [909.0, 915.0]}, "duration": 5.0, "duration_frame": 125.0, "duration_rounded": 6.0, "subset": "train", "url": "https://www.youtube.com/watch?v=hIQ8vcu01Ws"}}