{"HKlFAD4KHtY_0": {"annotations": {"label": "left", "segment": [112.04, 117.04]}, "annotations_frame": {"label": "left", "segment": [2801.0, 2926.0]}, "annotations_rounded": {"label": "left", "segment": [112.0, 118.0]}, "duration": 5.0, "duration_frame": 125.0, "duration_rounded": 6.0, "subset": "train", "url": "https://www.youtube.com/watch?v=HKlFAD4KHtY"}, "HKlFAD4KHtY_1": {"annotations": {"label": "left", "segment": [256.48, 261.48]}, "annotations_frame": {"label": "left", "segment": [6412.0, 6537.0]}, "annotations_rounded": {"label": "left", "segment": [256.0, 262.0]}, "duration": 5.0, "duration_frame": 125.0, "duration_rounded": 6.0, "subset": "train", "url": "https://www.youtube.com/watch?v=HKlFAD4KHtY"}, "HKlFAD4KHtY_2": {"annotations": {"label": "left", "segment": [350.6, 355.6]}, "annotations_frame": {"label": "left", "segment": [8765.0, 8890.0]}, "annotations_rounded": {"label": "left", "segment": [350.0, 356.0]}, "duration": 5.0, "duration_frame": 125.0, "duration_rounded": 6.0, "subset": "train", "url": "https://www.youtube.com/watch?v=HKlFAD4KHtY"}, "HKlFAD4KHtY_3": {"annotations": {"label": "left", "segment": [428.36, 433.36]}, "annotations_frame": {"label": "left", "segment": [10709.0, 10834.0]}, "annotations_rounded": {"label": "left", "segment": [428.0, 434.0]}, "duration": 5.0, "duration_frame": 125.0, "duration_rounded": 6.0, "subset": "train", "url": "https://www.youtube.com/watch?v=HKlFAD4KHtY"}, "HKlFAD4KHtY_4": {"annotations": {"label": "left", "segment": [477.4, 482.4]}, "annotations_frame": {"label": "left", "segment": [11935.0, 12060.0]}, "annotations_rounded": {"label": "left", "segment": [477.0, 483.0]}, "duration": 5.0, "duration_frame": 125.0, "duration_rounded": 6.0, "subset": "train", "url": "https://www.youtube.com/watch?v=HKlFAD4KHtY"}, "HKlFAD4KHtY_5": {"annotations": {"label": "right", "segment": [606.08, 611.08]}, "annotations_frame": {"label": "right", "segment": [15152.0, 15277.0]}, "annotations_rounded": {"label": "right", "segment": [606.0, 612.0]}, "duration": 5.0, "duration_frame": 125.0, "duration_rounded": 6.0, "subset": "train", "url": "https://www.youtube.com/watch?v=HKlFAD4KHtY"}, "HKlFAD4KHtY_6": {"annotations": {"label": "left", "segment": [694.12, 699.12]}, "annotations_frame": {"label": "left", "segment": [17353.0, 17478.0]}, "annotations_rounded": {"label": "left", "segment": [694.0, 700.0]}, "duration": 5.0, "duration_frame": 125.0, "duration_rounded": 6.0, "subset": "train", "url": "https://www.youtube.com/watch?v=HKlFAD4KHtY"}}