{"I-TewtDWTdk_0": {"annotations": {"label": "left", "segment": [61.56, 66.56]}, "annotations_frame": {"label": "left", "segment": [1539.0, 1664.0]}, "annotations_rounded": {"label": "left", "segment": [61.0, 67.0]}, "duration": 5.0, "duration_frame": 125.0, "duration_rounded": 6.0, "subset": "train", "url": "https://www.youtube.com/watch?v=I-TewtDWTdk"}, "I-TewtDWTdk_1": {"annotations": {"label": "left", "segment": [90.76, 95.76]}, "annotations_frame": {"label": "left", "segment": [2269.0, 2394.0]}, "annotations_rounded": {"label": "left", "segment": [90.0, 96.0]}, "duration": 5.0, "duration_frame": 125.0, "duration_rounded": 6.0, "subset": "train", "url": "https://www.youtube.com/watch?v=I-TewtDWTdk"}, "I-TewtDWTdk_2": {"annotations": {"label": "together", "segment": [291.72, 296.72]}, "annotations_frame": {"label": "together", "segment": [7293.0, 7418.0]}, "annotations_rounded": {"label": "together", "segment": [291.0, 297.0]}, "duration": 5.0, "duration_frame": 125.0, "duration_rounded": 6.0, "subset": "train", "url": "https://www.youtube.com/watch?v=I-TewtDWTdk"}, "I-TewtDWTdk_3": {"annotations": {"label": "together", "segment": [482.12, 487.12]}, "annotations_frame": {"label": "together", "segment": [12053.0, 12178.0]}, "annotations_rounded": {"label": "together", "segment": [482.0, 488.0]}, "duration": 5.0, "duration_frame": 125.0, "duration_rounded": 6.0, "subset": "train", "url": "https://www.youtube.com/watch?v=I-TewtDWTdk"}, "I-TewtDWTdk_4": {"annotations": {"label": "right", "segment": [686.36, 691.36]}, "annotations_frame": {"label": "right", "segment": [17159.0, 17284.0]}, "annotations_rounded": {"label": "right", "segment": [686.0, 692.0]}, "duration": 5.0, "duration_frame": 125.0, "duration_rounded": 6.0, "subset": "train", "url": "https://www.youtube.com/watch?v=I-TewtDWTdk"}, "I-TewtDWTdk_5": {"annotations": {"label": "left", "segment": [746.36, 751.36]}, "annotations_frame": {"label": "left", "segment": [18659.0, 18784.0]}, "annotations_rounded": {"label": "left", "segment": [746.0, 752.0]}, "duration": 5.0, "duration_frame": 125.0, "duration_rounded": 6.0, "subset": "train", "url": "https://www.youtube.com/watch?v=I-TewtDWTdk"}, "I-TewtDWTdk_6": {"annotations": {"label": "left", "segment": [837.52, 842.52]}, "annotations_frame": {"label": "left", "segment": [20938.0, 21063.0]}, "annotations_rounded": {"label": "left", "segment": [837.0, 843.0]}, "duration": 5.0, "duration_frame": 125.0, "duration_rounded": 6.0, "subset": "train", "url": "https://www.youtube.com/watch?v=I-TewtDWTdk"}, "I-TewtDWTdk_7": {"annotations": {"label": "right", "segment": [1007.92, 1012.92]}, "annotations_frame": {"label": "right", "segment": [25198.0, 25323.0]}, "annotations_rounded": {"label": "right", "segment": [1007.0, 1013.0]}, "duration": 5.0, "duration_frame": 125.0, "duration_rounded": 6.0, "subset": "train", "url": "https://www.youtube.com/watch?v=I-TewtDWTdk"}, "I-TewtDWTdk_8": {"annotations": {"label": "together", "segment": [1128.8, 1133.8]}, "annotations_frame": {"label": "together", "segment": [28220.0, 28345.0]}, "annotations_rounded": {"label": "together", "segment": [1128.0, 1134.0]}, "duration": 5.0, "duration_frame": 125.0, "duration_rounded": 6.0, "subset": "train", "url": "https://www.youtube.com/watch?v=I-TewtDWTdk"}, "I-TewtDWTdk_9": {"annotations": {"label": "right", "segment": [1277.24, 1282.24]}, "annotations_frame": {"label": "right", "segment": [31931.0, 32056.0]}, "annotations_rounded": {"label": "right", "segment": [1277.0, 1283.0]}, "duration": 5.0, "duration_frame": 125.0, "duration_rounded": 6.0, "subset": "train", "url": "https://www.youtube.com/watch?v=I-TewtDWTdk"}}