{"keJ6EA5uKa4_0": {"annotations": {"label": "right", "segment": [127.2, 132.2]}, "annotations_frame": {"label": "right", "segment": [3180.0, 3305.0]}, "annotations_rounded": {"label": "right", "segment": [127.0, 133.0]}, "duration": 4.999999999999986, "duration_frame": 125.0, "duration_rounded": 6.0, "subset": "train", "url": "https://www.youtube.com/watch?v=keJ6EA5uKa4"}, "keJ6EA5uKa4_1": {"annotations": {"label": "right", "segment": [200.84, 205.84]}, "annotations_frame": {"label": "right", "segment": [5021.0, 5146.0]}, "annotations_rounded": {"label": "right", "segment": [200.0, 206.0]}, "duration": 5.0, "duration_frame": 125.0, "duration_rounded": 6.0, "subset": "train", "url": "https://www.youtube.com/watch?v=keJ6EA5uKa4"}, "keJ6EA5uKa4_2": {"annotations": {"label": "right", "segment": [289.36, 294.36]}, "annotations_frame": {"label": "right", "segment": [7234.0, 7359.0]}, "annotations_rounded": {"label": "right", "segment": [289.0, 295.0]}, "duration": 5.0, "duration_frame": 125.0, "duration_rounded": 6.0, "subset": "train", "url": "https://www.youtube.com/watch?v=keJ6EA5uKa4"}, "keJ6EA5uKa4_3": {"annotations": {"label": "together", "segment": [533.44, 538.44]}, "annotations_frame": {"label": "together", "segment": [13336.0, 13461.0]}, "annotations_rounded": {"label": "together", "segment": [533.0, 539.0]}, "duration": 5.0, "duration_frame": 125.0, "duration_rounded": 6.0, "subset": "train", "url": "https://www.youtube.com/watch?v=keJ6EA5uKa4"}, "keJ6EA5uKa4_4": {"annotations": {"label": "right", "segment": [578.2, 583.2]}, "annotations_frame": {"label": "right", "segment": [14455.0, 14580.0]}, "annotations_rounded": {"label": "right", "segment": [578.0, 584.0]}, "duration": 5.0, "duration_frame": 125.0, "duration_rounded": 6.0, "subset": "train", "url": "https://www.youtube.com/watch?v=keJ6EA5uKa4"}, "keJ6EA5uKa4_5": {"annotations": {"label": "right", "segment": [613.72, 618.72]}, "annotations_frame": {"label": "right", "segment": [15343.0, 15468.0]}, "annotations_rounded": {"label": "right", "segment": [613.0, 619.0]}, "duration": 5.0, "duration_frame": 125.0, "duration_rounded": 6.0, "subset": "train", "url": "https://www.youtube.com/watch?v=keJ6EA5uKa4"}, "keJ6EA5uKa4_6": {"annotations": {"label": "right", "segment": [660.4, 665.4]}, "annotations_frame": {"label": "right", "segment": [16510.0, 16635.0]}, "annotations_rounded": {"label": "right", "segment": [660.0, 666.0]}, "duration": 5.0, "duration_frame": 125.0, "duration_rounded": 6.0, "subset": "train", "url": "https://www.youtube.com/watch?v=keJ6EA5uKa4"}}