{"kOuUngL2fsU_0": {"annotations": {"label": "together", "segment": [185.36, 190.36]}, "annotations_frame": {"label": "together", "segment": [4634.0, 4759.0]}, "annotations_rounded": {"label": "together", "segment": [185.0, 191.0]}, "duration": 5.0, "duration_frame": 125.0, "duration_rounded": 6.0, "subset": "train", "url": "https://www.youtube.com/watch?v=kOuUngL2fsU"}, "kOuUngL2fsU_1": {"annotations": {"label": "right", "segment": [358.04, 363.04]}, "annotations_frame": {"label": "right", "segment": [8951.0, 9076.0]}, "annotations_rounded": {"label": "right", "segment": [358.0, 364.0]}, "duration": 5.0, "duration_frame": 125.0, "duration_rounded": 6.0, "subset": "train", "url": "https://www.youtube.com/watch?v=kOuUngL2fsU"}, "kOuUngL2fsU_2": {"annotations": {"label": "left", "segment": [369.68, 374.68]}, "annotations_frame": {"label": "left", "segment": [9242.0, 9367.0]}, "annotations_rounded": {"label": "left", "segment": [369.0, 375.0]}, "duration": 5.0, "duration_frame": 125.0, "duration_rounded": 6.0, "subset": "train", "url": "https://www.youtube.com/watch?v=kOuUngL2fsU"}, "kOuUngL2fsU_3": {"annotations": {"label": "together", "segment": [509.48, 514.48]}, "annotations_frame": {"label": "together", "segment": [12737.0, 12862.0]}, "annotations_rounded": {"label": "together", "segment": [509.0, 515.0]}, "duration": 5.0, "duration_frame": 125.0, "duration_rounded": 6.0, "subset": "train", "url": "https://www.youtube.com/watch?v=kOuUngL2fsU"}, "kOuUngL2fsU_4": {"annotations": {"label": "together", "segment": [618.44, 623.44]}, "annotations_frame": {"label": "together", "segment": [15461.0, 15586.0]}, "annotations_rounded": {"label": "together", "segment": [618.0, 624.0]}, "duration": 5.0, "duration_frame": 125.0, "duration_rounded": 6.0, "subset": "train", "url": "https://www.youtube.com/watch?v=kOuUngL2fsU"}, "kOuUngL2fsU_5": {"annotations": {"label": "left", "segment": [641.56, 646.56]}, "annotations_frame": {"label": "left", "segment": [16039.0, 16164.0]}, "annotations_rounded": {"label": "left", "segment": [641.0, 647.0]}, "duration": 5.0, "duration_frame": 125.0, "duration_rounded": 6.0, "subset": "train", "url": "https://www.youtube.com/watch?v=kOuUngL2fsU"}, "kOuUngL2fsU_6": {"annotations": {"label": "together", "segment": [1153.08, 1158.08]}, "annotations_frame": {"label": "together", "segment": [28827.0, 28952.0]}, "annotations_rounded": {"label": "together", "segment": [1153.0, 1159.0]}, "duration": 5.0, "duration_frame": 125.0, "duration_rounded": 6.0, "subset": "train", "url": "https://www.youtube.com/watch?v=kOuUngL2fsU"}, "kOuUngL2fsU_7": {"annotations": {"label": "right", "segment": [1175.48, 1180.48]}, "annotations_frame": {"label": "right", "segment": [29387.0, 29512.0]}, "annotations_rounded": {"label": "right", "segment": [1175.0, 1181.0]}, "duration": 5.0, "duration_frame": 125.0, "duration_rounded": 6.0, "subset": "train", "url": "https://www.youtube.com/watch?v=kOuUngL2fsU"}, "kOuUngL2fsU_8": {"annotations": {"label": "right", "segment": [1358.72, 1363.72]}, "annotations_frame": {"label": "right", "segment": [33968.0, 34093.0]}, "annotations_rounded": {"label": "right", "segment": [1358.0, 1364.0]}, "duration": 5.0, "duration_frame": 125.0, "duration_rounded": 6.0, "subset": "train", "url": "https://www.youtube.com/watch?v=kOuUngL2fsU"}, "kOuUngL2fsU_9": {"annotations": {"label": "right", "segment": [1561.8, 1566.8]}, "annotations_frame": {"label": "right", "segment": [39045.0, 39170.0]}, "annotations_rounded": {"label": "right", "segment": [1561.0, 1567.0]}, "duration": 5.0, "duration_frame": 125.0, "duration_rounded": 6.0, "subset": "train", "url": "https://www.youtube.com/watch?v=kOuUngL2fsU"}, "kOuUngL2fsU_10": {"annotations": {"label": "right", "segment": [1603.2, 1608.2]}, "annotations_frame": {"label": "right", "segment": [40080.0, 40205.0]}, "annotations_rounded": {"label": "right", "segment": [1603.0, 1609.0]}, "duration": 5.0, "duration_frame": 125.0, "duration_rounded": 6.0, "subset": "train", "url": "https://www.youtube.com/watch?v=kOuUngL2fsU"}, "kOuUngL2fsU_11": {"annotations": {"label": "together", "segment": [1700.88, 1705.88]}, "annotations_frame": {"label": "together", "segment": [42522.0, 42647.0]}, "annotations_rounded": {"label": "together", "segment": [1700.0, 1706.0]}, "duration": 5.0, "duration_frame": 125.0, "duration_rounded": 6.0, "subset": "train", "url": "https://www.youtube.com/watch?v=kOuUngL2fsU"}}