{"LhugkqcoD18_0": {"annotations": {"label": "right", "segment": [130.36, 135.36]}, "annotations_frame": {"label": "right", "segment": [3259.0, 3384.0]}, "annotations_rounded": {"label": "right", "segment": [130.0, 136.0]}, "duration": 5.0, "duration_frame": 125.0, "duration_rounded": 6.0, "subset": "train", "url": "https://www.youtube.com/watch?v=LhugkqcoD18"}, "LhugkqcoD18_1": {"annotations": {"label": "right", "segment": [239.92, 244.92]}, "annotations_frame": {"label": "right", "segment": [5998.0, 6123.0]}, "annotations_rounded": {"label": "right", "segment": [239.0, 245.0]}, "duration": 5.0, "duration_frame": 125.0, "duration_rounded": 6.0, "subset": "train", "url": "https://www.youtube.com/watch?v=LhugkqcoD18"}, "LhugkqcoD18_2": {"annotations": {"label": "right", "segment": [301.56, 306.56]}, "annotations_frame": {"label": "right", "segment": [7539.0, 7664.0]}, "annotations_rounded": {"label": "right", "segment": [301.0, 307.0]}, "duration": 5.0, "duration_frame": 125.0, "duration_rounded": 6.0, "subset": "train", "url": "https://www.youtube.com/watch?v=LhugkqcoD18"}, "LhugkqcoD18_3": {"annotations": {"label": "left", "segment": [395.56, 400.56]}, "annotations_frame": {"label": "left", "segment": [9889.0, 10014.0]}, "annotations_rounded": {"label": "left", "segment": [395.0, 401.0]}, "duration": 5.0, "duration_frame": 125.0, "duration_rounded": 6.0, "subset": "train", "url": "https://www.youtube.com/watch?v=LhugkqcoD18"}, "LhugkqcoD18_4": {"annotations": {"label": "left", "segment": [457.6, 462.6]}, "annotations_frame": {"label": "left", "segment": [11440.0, 11565.0]}, "annotations_rounded": {"label": "left", "segment": [457.0, 463.0]}, "duration": 5.0, "duration_frame": 125.0, "duration_rounded": 6.0, "subset": "train", "url": "https://www.youtube.com/watch?v=LhugkqcoD18"}, "LhugkqcoD18_5": {"annotations": {"label": "left", "segment": [489.32, 494.32]}, "annotations_frame": {"label": "left", "segment": [12233.0, 12358.0]}, "annotations_rounded": {"label": "left", "segment": [489.0, 495.0]}, "duration": 5.0, "duration_frame": 125.0, "duration_rounded": 6.0, "subset": "train", "url": "https://www.youtube.com/watch?v=LhugkqcoD18"}, "LhugkqcoD18_6": {"annotations": {"label": "right", "segment": [533.08, 538.08]}, "annotations_frame": {"label": "right", "segment": [13327.0, 13452.0]}, "annotations_rounded": {"label": "right", "segment": [533.0, 539.0]}, "duration": 5.0, "duration_frame": 125.0, "duration_rounded": 6.0, "subset": "train", "url": "https://www.youtube.com/watch?v=LhugkqcoD18"}, "LhugkqcoD18_7": {"annotations": {"label": "together", "segment": [667.36, 672.36]}, "annotations_frame": {"label": "together", "segment": [16684.0, 16809.0]}, "annotations_rounded": {"label": "together", "segment": [667.0, 673.0]}, "duration": 5.0, "duration_frame": 125.0, "duration_rounded": 6.0, "subset": "train", "url": "https://www.youtube.com/watch?v=LhugkqcoD18"}, "LhugkqcoD18_8": {"annotations": {"label": "left", "segment": [720.0, 725.0]}, "annotations_frame": {"label": "left", "segment": [18000.0, 18125.0]}, "annotations_rounded": {"label": "left", "segment": [720.0, 725.0]}, "duration": 5.0, "duration_frame": 125.0, "duration_rounded": 5.0, "subset": "train", "url": "https://www.youtube.com/watch?v=LhugkqcoD18"}}