{"NmQ8WPLYDq4_0": {"annotations": {"label": "together", "segment": [640.92, 645.92]}, "annotations_frame": {"label": "together", "segment": [16023.0, 16148.0]}, "annotations_rounded": {"label": "together", "segment": [640.0, 646.0]}, "duration": 5.0, "duration_frame": 125.0, "duration_rounded": 6.0, "subset": "train", "url": "https://www.youtube.com/watch?v=NmQ8WPLYDq4"}, "NmQ8WPLYDq4_1": {"annotations": {"label": "left", "segment": [1013.68, 1018.68]}, "annotations_frame": {"label": "left", "segment": [25342.0, 25467.0]}, "annotations_rounded": {"label": "left", "segment": [1013.0, 1019.0]}, "duration": 5.0, "duration_frame": 125.0, "duration_rounded": 6.0, "subset": "train", "url": "https://www.youtube.com/watch?v=NmQ8WPLYDq4"}, "NmQ8WPLYDq4_2": {"annotations": {"label": "together", "segment": [1147.72, 1152.72]}, "annotations_frame": {"label": "together", "segment": [28693.0, 28818.0]}, "annotations_rounded": {"label": "together", "segment": [1147.0, 1153.0]}, "duration": 5.0, "duration_frame": 125.0, "duration_rounded": 6.0, "subset": "train", "url": "https://www.youtube.com/watch?v=NmQ8WPLYDq4"}, "NmQ8WPLYDq4_3": {"annotations": {"label": "right", "segment": [1274.84, 1279.84]}, "annotations_frame": {"label": "right", "segment": [31871.0, 31996.0]}, "annotations_rounded": {"label": "right", "segment": [1274.0, 1280.0]}, "duration": 5.0, "duration_frame": 125.0, "duration_rounded": 6.0, "subset": "train", "url": "https://www.youtube.com/watch?v=NmQ8WPLYDq4"}, "NmQ8WPLYDq4_4": {"annotations": {"label": "together", "segment": [1424.44, 1429.44]}, "annotations_frame": {"label": "together", "segment": [35611.0, 35736.0]}, "annotations_rounded": {"label": "together", "segment": [1424.0, 1430.0]}, "duration": 5.0, "duration_frame": 125.0, "duration_rounded": 6.0, "subset": "train", "url": "https://www.youtube.com/watch?v=NmQ8WPLYDq4"}, "NmQ8WPLYDq4_5": {"annotations": {"label": "left", "segment": [1456.6, 1461.6]}, "annotations_frame": {"label": "left", "segment": [36415.0, 36540.0]}, "annotations_rounded": {"label": "left", "segment": [1456.0, 1462.0]}, "duration": 5.0, "duration_frame": 125.0, "duration_rounded": 6.0, "subset": "train", "url": "https://www.youtube.com/watch?v=NmQ8WPLYDq4"}, "NmQ8WPLYDq4_6": {"annotations": {"label": "together", "segment": [1634.2, 1639.2]}, "annotations_frame": {"label": "together", "segment": [40855.0, 40980.0]}, "annotations_rounded": {"label": "together", "segment": [1634.0, 1640.0]}, "duration": 5.0, "duration_frame": 125.0, "duration_rounded": 6.0, "subset": "train", "url": "https://www.youtube.com/watch?v=NmQ8WPLYDq4"}}