{"RxbM3EAVqaE_0": {"annotations": {"label": "right", "segment": [153.84, 158.84]}, "annotations_frame": {"label": "right", "segment": [3846.0, 3971.0]}, "annotations_rounded": {"label": "right", "segment": [153.0, 159.0]}, "duration": 5.0, "duration_frame": 125.0, "duration_rounded": 6.0, "subset": "train", "url": "https://www.youtube.com/watch?v=RxbM3EAVqaE"}, "RxbM3EAVqaE_1": {"annotations": {"label": "together", "segment": [241.88, 246.88]}, "annotations_frame": {"label": "together", "segment": [6047.0, 6172.0]}, "annotations_rounded": {"label": "together", "segment": [241.0, 247.0]}, "duration": 5.0, "duration_frame": 125.0, "duration_rounded": 6.0, "subset": "train", "url": "https://www.youtube.com/watch?v=RxbM3EAVqaE"}, "RxbM3EAVqaE_2": {"annotations": {"label": "right", "segment": [306.0, 311.0]}, "annotations_frame": {"label": "right", "segment": [7650.0, 7775.0]}, "annotations_rounded": {"label": "right", "segment": [306.0, 311.0]}, "duration": 5.0, "duration_frame": 125.0, "duration_rounded": 5.0, "subset": "train", "url": "https://www.youtube.com/watch?v=RxbM3EAVqaE"}, "RxbM3EAVqaE_3": {"annotations": {"label": "right", "segment": [407.76, 412.76]}, "annotations_frame": {"label": "right", "segment": [10194.0, 10319.0]}, "annotations_rounded": {"label": "right", "segment": [407.0, 413.0]}, "duration": 5.0, "duration_frame": 125.0, "duration_rounded": 6.0, "subset": "train", "url": "https://www.youtube.com/watch?v=RxbM3EAVqaE"}, "RxbM3EAVqaE_4": {"annotations": {"label": "right", "segment": [561.28, 566.28]}, "annotations_frame": {"label": "right", "segment": [14032.0, 14157.0]}, "annotations_rounded": {"label": "right", "segment": [561.0, 567.0]}, "duration": 5.0, "duration_frame": 125.0, "duration_rounded": 6.0, "subset": "train", "url": "https://www.youtube.com/watch?v=RxbM3EAVqaE"}, "RxbM3EAVqaE_5": {"annotations": {"label": "left", "segment": [585.88, 590.88]}, "annotations_frame": {"label": "left", "segment": [14647.0, 14772.0]}, "annotations_rounded": {"label": "left", "segment": [585.0, 591.0]}, "duration": 5.0, "duration_frame": 125.0, "duration_rounded": 6.0, "subset": "train", "url": "https://www.youtube.com/watch?v=RxbM3EAVqaE"}, "RxbM3EAVqaE_6": {"annotations": {"label": "together", "segment": [663.48, 668.48]}, "annotations_frame": {"label": "together", "segment": [16587.0, 16712.0]}, "annotations_rounded": {"label": "together", "segment": [663.0, 669.0]}, "duration": 5.0, "duration_frame": 125.0, "duration_rounded": 6.0, "subset": "train", "url": "https://www.youtube.com/watch?v=RxbM3EAVqaE"}, "RxbM3EAVqaE_7": {"annotations": {"label": "right", "segment": [712.76, 717.76]}, "annotations_frame": {"label": "right", "segment": [17819.0, 17944.0]}, "annotations_rounded": {"label": "right", "segment": [712.0, 718.0]}, "duration": 5.0, "duration_frame": 125.0, "duration_rounded": 6.0, "subset": "train", "url": "https://www.youtube.com/watch?v=RxbM3EAVqaE"}}