{"sNS8WKc1vlc_0": {"annotations": {"label": "left", "segment": [158.24, 163.24]}, "annotations_frame": {"label": "left", "segment": [3956.0, 4081.0]}, "annotations_rounded": {"label": "left", "segment": [158.0, 164.0]}, "duration": 5.0, "duration_frame": 125.0, "duration_rounded": 6.0, "subset": "train", "url": "https://www.youtube.com/watch?v=sNS8WKc1vlc"}, "sNS8WKc1vlc_1": {"annotations": {"label": "left", "segment": [277.92, 282.92]}, "annotations_frame": {"label": "left", "segment": [6948.0, 7073.0]}, "annotations_rounded": {"label": "left", "segment": [277.0, 283.0]}, "duration": 5.0, "duration_frame": 125.0, "duration_rounded": 6.0, "subset": "train", "url": "https://www.youtube.com/watch?v=sNS8WKc1vlc"}, "sNS8WKc1vlc_2": {"annotations": {"label": "together", "segment": [429.24, 434.24]}, "annotations_frame": {"label": "together", "segment": [10731.0, 10856.0]}, "annotations_rounded": {"label": "together", "segment": [429.0, 435.0]}, "duration": 5.0, "duration_frame": 125.0, "duration_rounded": 6.0, "subset": "train", "url": "https://www.youtube.com/watch?v=sNS8WKc1vlc"}, "sNS8WKc1vlc_3": {"annotations": {"label": "together", "segment": [887.68, 892.68]}, "annotations_frame": {"label": "together", "segment": [22192.0, 22317.0]}, "annotations_rounded": {"label": "together", "segment": [887.0, 893.0]}, "duration": 5.0, "duration_frame": 125.0, "duration_rounded": 6.0, "subset": "train", "url": "https://www.youtube.com/watch?v=sNS8WKc1vlc"}, "sNS8WKc1vlc_4": {"annotations": {"label": "together", "segment": [1046.56, 1051.56]}, "annotations_frame": {"label": "together", "segment": [26164.0, 26289.0]}, "annotations_rounded": {"label": "together", "segment": [1046.0, 1052.0]}, "duration": 5.0, "duration_frame": 125.0, "duration_rounded": 6.0, "subset": "train", "url": "https://www.youtube.com/watch?v=sNS8WKc1vlc"}, "sNS8WKc1vlc_5": {"annotations": {"label": "together", "segment": [1140.76, 1145.76]}, "annotations_frame": {"label": "together", "segment": [28519.0, 28644.0]}, "annotations_rounded": {"label": "together", "segment": [1140.0, 1146.0]}, "duration": 5.0, "duration_frame": 125.0, "duration_rounded": 6.0, "subset": "train", "url": "https://www.youtube.com/watch?v=sNS8WKc1vlc"}}