{"t_7nbGUQ0Zg_0": {"annotations": {"label": "together", "segment": [123.44, 128.44]}, "annotations_frame": {"label": "together", "segment": [3086.0, 3211.0]}, "annotations_rounded": {"label": "together", "segment": [123.0, 129.0]}, "duration": 5.0, "duration_frame": 125.0, "duration_rounded": 6.0, "subset": "train", "url": "https://www.youtube.com/watch?v=t_7nbGUQ0Zg"}, "t_7nbGUQ0Zg_1": {"annotations": {"label": "left", "segment": [138.88, 143.88]}, "annotations_frame": {"label": "left", "segment": [3472.0, 3597.0]}, "annotations_rounded": {"label": "left", "segment": [138.0, 144.0]}, "duration": 5.0, "duration_frame": 125.0, "duration_rounded": 6.0, "subset": "train", "url": "https://www.youtube.com/watch?v=t_7nbGUQ0Zg"}, "t_7nbGUQ0Zg_2": {"annotations": {"label": "left", "segment": [152.88, 157.88]}, "annotations_frame": {"label": "left", "segment": [3822.0, 3947.0]}, "annotations_rounded": {"label": "left", "segment": [152.0, 158.0]}, "duration": 5.0, "duration_frame": 125.0, "duration_rounded": 6.0, "subset": "train", "url": "https://www.youtube.com/watch?v=t_7nbGUQ0Zg"}, "t_7nbGUQ0Zg_3": {"annotations": {"label": "right", "segment": [269.68, 274.68]}, "annotations_frame": {"label": "right", "segment": [6742.0, 6867.0]}, "annotations_rounded": {"label": "right", "segment": [269.0, 275.0]}, "duration": 5.0, "duration_frame": 125.0, "duration_rounded": 6.0, "subset": "train", "url": "https://www.youtube.com/watch?v=t_7nbGUQ0Zg"}, "t_7nbGUQ0Zg_4": {"annotations": {"label": "together", "segment": [423.04, 428.04]}, "annotations_frame": {"label": "together", "segment": [10576.0, 10701.0]}, "annotations_rounded": {"label": "together", "segment": [423.0, 429.0]}, "duration": 5.0, "duration_frame": 125.0, "duration_rounded": 6.0, "subset": "train", "url": "https://www.youtube.com/watch?v=t_7nbGUQ0Zg"}, "t_7nbGUQ0Zg_5": {"annotations": {"label": "together", "segment": [518.6, 523.6]}, "annotations_frame": {"label": "together", "segment": [12965.0, 13090.0]}, "annotations_rounded": {"label": "together", "segment": [518.0, 524.0]}, "duration": 5.0, "duration_frame": 125.0, "duration_rounded": 6.0, "subset": "train", "url": "https://www.youtube.com/watch?v=t_7nbGUQ0Zg"}, "t_7nbGUQ0Zg_6": {"annotations": {"label": "left", "segment": [736.2, 741.2]}, "annotations_frame": {"label": "left", "segment": [18405.0, 18530.0]}, "annotations_rounded": {"label": "left", "segment": [736.0, 742.0]}, "duration": 5.0, "duration_frame": 125.0, "duration_rounded": 6.0, "subset": "train", "url": "https://www.youtube.com/watch?v=t_7nbGUQ0Zg"}, "t_7nbGUQ0Zg_7": {"annotations": {"label": "together", "segment": [836.48, 841.48]}, "annotations_frame": {"label": "together", "segment": [20912.0, 21037.0]}, "annotations_rounded": {"label": "together", "segment": [836.0, 842.0]}, "duration": 5.0, "duration_frame": 125.0, "duration_rounded": 6.0, "subset": "train", "url": "https://www.youtube.com/watch?v=t_7nbGUQ0Zg"}, "t_7nbGUQ0Zg_8": {"annotations": {"label": "together", "segment": [890.68, 895.68]}, "annotations_frame": {"label": "together", "segment": [22267.0, 22392.0]}, "annotations_rounded": {"label": "together", "segment": [890.0, 896.0]}, "duration": 5.0, "duration_frame": 125.0, "duration_rounded": 6.0, "subset": "train", "url": "https://www.youtube.com/watch?v=t_7nbGUQ0Zg"}, "t_7nbGUQ0Zg_9": {"annotations": {"label": "left", "segment": [905.84, 910.84]}, "annotations_frame": {"label": "left", "segment": [22646.0, 22771.0]}, "annotations_rounded": {"label": "left", "segment": [905.0, 911.0]}, "duration": 5.0, "duration_frame": 125.0, "duration_rounded": 6.0, "subset": "train", "url": "https://www.youtube.com/watch?v=t_7nbGUQ0Zg"}, "t_7nbGUQ0Zg_10": {"annotations": {"label": "left", "segment": [1036.72, 1041.72]}, "annotations_frame": {"label": "left", "segment": [25918.0, 26043.0]}, "annotations_rounded": {"label": "left", "segment": [1036.0, 1042.0]}, "duration": 5.0, "duration_frame": 125.0, "duration_rounded": 6.0, "subset": "train", "url": "https://www.youtube.com/watch?v=t_7nbGUQ0Zg"}, "t_7nbGUQ0Zg_11": {"annotations": {"label": "together", "segment": [1410.44, 1415.44]}, "annotations_frame": {"label": "together", "segment": [35261.0, 35386.0]}, "annotations_rounded": {"label": "together", "segment": [1410.0, 1416.0]}, "duration": 5.0, "duration_frame": 125.0, "duration_rounded": 6.0, "subset": "train", "url": "https://www.youtube.com/watch?v=t_7nbGUQ0Zg"}}