{"uUYHlfPgzb0_0": {"annotations": {"label": "together", "segment": [354.16, 359.16]}, "annotations_frame": {"label": "together", "segment": [8854.0, 8979.0]}, "annotations_rounded": {"label": "together", "segment": [354.0, 360.0]}, "duration": 5.0, "duration_frame": 125.0, "duration_rounded": 6.0, "subset": "train", "url": "https://www.youtube.com/watch?v=uUYHlfPgzb0"}, "uUYHlfPgzb0_1": {"annotations": {"label": "together", "segment": [676.52, 681.52]}, "annotations_frame": {"label": "together", "segment": [16913.0, 17038.0]}, "annotations_rounded": {"label": "together", "segment": [676.0, 682.0]}, "duration": 5.0, "duration_frame": 125.0, "duration_rounded": 6.0, "subset": "train", "url": "https://www.youtube.com/watch?v=uUYHlfPgzb0"}, "uUYHlfPgzb0_2": {"annotations": {"label": "left", "segment": [715.8, 720.8]}, "annotations_frame": {"label": "left", "segment": [17895.0, 18020.0]}, "annotations_rounded": {"label": "left", "segment": [715.0, 721.0]}, "duration": 5.0, "duration_frame": 125.0, "duration_rounded": 6.0, "subset": "train", "url": "https://www.youtube.com/watch?v=uUYHlfPgzb0"}, "uUYHlfPgzb0_3": {"annotations": {"label": "left", "segment": [944.8, 949.8]}, "annotations_frame": {"label": "left", "segment": [23620.0, 23745.0]}, "annotations_rounded": {"label": "left", "segment": [944.0, 950.0]}, "duration": 5.0, "duration_frame": 125.0, "duration_rounded": 6.0, "subset": "train", "url": "https://www.youtube.com/watch?v=uUYHlfPgzb0"}, "uUYHlfPgzb0_4": {"annotations": {"label": "together", "segment": [980.56, 985.56]}, "annotations_frame": {"label": "together", "segment": [24514.0, 24639.0]}, "annotations_rounded": {"label": "together", "segment": [980.0, 986.0]}, "duration": 5.0, "duration_frame": 125.0, "duration_rounded": 6.0, "subset": "train", "url": "https://www.youtube.com/watch?v=uUYHlfPgzb0"}}