{"xe2M4xF2SkI_0": {"annotations": {"label": "right", "segment": [189.16, 194.16]}, "annotations_frame": {"label": "right", "segment": [4729.0, 4854.0]}, "annotations_rounded": {"label": "right", "segment": [189.0, 195.0]}, "duration": 5.0, "duration_frame": 125.0, "duration_rounded": 6.0, "subset": "train", "url": "https://www.youtube.com/watch?v=xe2M4xF2SkI"}, "xe2M4xF2SkI_1": {"annotations": {"label": "left", "segment": [314.44, 319.44]}, "annotations_frame": {"label": "left", "segment": [7861.0, 7986.0]}, "annotations_rounded": {"label": "left", "segment": [314.0, 320.0]}, "duration": 5.0, "duration_frame": 125.0, "duration_rounded": 6.0, "subset": "train", "url": "https://www.youtube.com/watch?v=xe2M4xF2SkI"}, "xe2M4xF2SkI_2": {"annotations": {"label": "right", "segment": [352.64, 357.64]}, "annotations_frame": {"label": "right", "segment": [8816.0, 8941.0]}, "annotations_rounded": {"label": "right", "segment": [352.0, 358.0]}, "duration": 5.0, "duration_frame": 125.0, "duration_rounded": 6.0, "subset": "train", "url": "https://www.youtube.com/watch?v=xe2M4xF2SkI"}, "xe2M4xF2SkI_3": {"annotations": {"label": "right", "segment": [409.28, 414.28]}, "annotations_frame": {"label": "right", "segment": [10232.0, 10357.0]}, "annotations_rounded": {"label": "right", "segment": [409.0, 415.0]}, "duration": 5.0, "duration_frame": 125.0, "duration_rounded": 6.0, "subset": "train", "url": "https://www.youtube.com/watch?v=xe2M4xF2SkI"}, "xe2M4xF2SkI_4": {"annotations": {"label": "right", "segment": [425.56, 430.56]}, "annotations_frame": {"label": "right", "segment": [10639.0, 10764.0]}, "annotations_rounded": {"label": "right", "segment": [425.0, 431.0]}, "duration": 5.0, "duration_frame": 125.0, "duration_rounded": 6.0, "subset": "train", "url": "https://www.youtube.com/watch?v=xe2M4xF2SkI"}, "xe2M4xF2SkI_5": {"annotations": {"label": "together", "segment": [503.92, 508.92]}, "annotations_frame": {"label": "together", "segment": [12598.0, 12723.0]}, "annotations_rounded": {"label": "together", "segment": [503.0, 509.0]}, "duration": 5.0, "duration_frame": 125.0, "duration_rounded": 6.0, "subset": "train", "url": "https://www.youtube.com/watch?v=xe2M4xF2SkI"}, "xe2M4xF2SkI_6": {"annotations": {"label": "left", "segment": [725.44, 730.44]}, "annotations_frame": {"label": "left", "segment": [18136.0, 18261.0]}, "annotations_rounded": {"label": "left", "segment": [725.0, 731.0]}, "duration": 5.0, "duration_frame": 125.0, "duration_rounded": 6.0, "subset": "train", "url": "https://www.youtube.com/watch?v=xe2M4xF2SkI"}, "xe2M4xF2SkI_7": {"annotations": {"label": "left", "segment": [767.04, 772.04]}, "annotations_frame": {"label": "left", "segment": [19176.0, 19301.0]}, "annotations_rounded": {"label": "left", "segment": [767.0, 773.0]}, "duration": 5.0, "duration_frame": 125.0, "duration_rounded": 6.0, "subset": "train", "url": "https://www.youtube.com/watch?v=xe2M4xF2SkI"}}