{"Y_tLNYQfjv0_0": {"annotations": {"label": "left", "segment": [84.44, 89.44]}, "annotations_frame": {"label": "left", "segment": [2111.0, 2236.0]}, "annotations_rounded": {"label": "left", "segment": [84.0, 90.0]}, "duration": 5.0, "duration_frame": 125.0, "duration_rounded": 6.0, "subset": "train", "url": "https://www.youtube.com/watch?v=Y_tLNYQfjv0"}, "Y_tLNYQfjv0_1": {"annotations": {"label": "right", "segment": [158.32, 163.32]}, "annotations_frame": {"label": "right", "segment": [3958.0, 4083.0]}, "annotations_rounded": {"label": "right", "segment": [158.0, 164.0]}, "duration": 5.0, "duration_frame": 125.0, "duration_rounded": 6.0, "subset": "train", "url": "https://www.youtube.com/watch?v=Y_tLNYQfjv0"}, "Y_tLNYQfjv0_2": {"annotations": {"label": "together", "segment": [282.2, 287.2]}, "annotations_frame": {"label": "together", "segment": [7055.0, 7180.0]}, "annotations_rounded": {"label": "together", "segment": [282.0, 288.0]}, "duration": 5.0, "duration_frame": 125.0, "duration_rounded": 6.0, "subset": "train", "url": "https://www.youtube.com/watch?v=Y_tLNYQfjv0"}, "Y_tLNYQfjv0_3": {"annotations": {"label": "right", "segment": [327.04, 332.04]}, "annotations_frame": {"label": "right", "segment": [8176.0, 8301.0]}, "annotations_rounded": {"label": "right", "segment": [327.0, 333.0]}, "duration": 5.0, "duration_frame": 125.0, "duration_rounded": 6.0, "subset": "train", "url": "https://www.youtube.com/watch?v=Y_tLNYQfjv0"}, "Y_tLNYQfjv0_4": {"annotations": {"label": "together", "segment": [348.0, 353.0]}, "annotations_frame": {"label": "together", "segment": [8700.0, 8825.0]}, "annotations_rounded": {"label": "together", "segment": [348.0, 353.0]}, "duration": 5.0, "duration_frame": 125.0, "duration_rounded": 5.0, "subset": "train", "url": "https://www.youtube.com/watch?v=Y_tLNYQfjv0"}, "Y_tLNYQfjv0_5": {"annotations": {"label": "together", "segment": [404.0, 409.0]}, "annotations_frame": {"label": "together", "segment": [10100.0, 10225.0]}, "annotations_rounded": {"label": "together", "segment": [404.0, 409.0]}, "duration": 5.0, "duration_frame": 125.0, "duration_rounded": 5.0, "subset": "train", "url": "https://www.youtube.com/watch?v=Y_tLNYQfjv0"}, "Y_tLNYQfjv0_6": {"annotations": {"label": "left", "segment": [436.4, 441.4]}, "annotations_frame": {"label": "left", "segment": [10910.0, 11035.0]}, "annotations_rounded": {"label": "left", "segment": [436.0, 442.0]}, "duration": 5.0, "duration_frame": 125.0, "duration_rounded": 6.0, "subset": "train", "url": "https://www.youtube.com/watch?v=Y_tLNYQfjv0"}, "Y_tLNYQfjv0_7": {"annotations": {"label": "right", "segment": [452.04, 457.04]}, "annotations_frame": {"label": "right", "segment": [11301.0, 11426.0]}, "annotations_rounded": {"label": "right", "segment": [452.0, 458.0]}, "duration": 5.0, "duration_frame": 125.0, "duration_rounded": 6.0, "subset": "train", "url": "https://www.youtube.com/watch?v=Y_tLNYQfjv0"}, "Y_tLNYQfjv0_8": {"annotations": {"label": "right", "segment": [544.6, 549.6]}, "annotations_frame": {"label": "right", "segment": [13615.0, 13740.0]}, "annotations_rounded": {"label": "right", "segment": [544.0, 550.0]}, "duration": 5.0, "duration_frame": 125.0, "duration_rounded": 6.0, "subset": "train", "url": "https://www.youtube.com/watch?v=Y_tLNYQfjv0"}, "Y_tLNYQfjv0_9": {"annotations": {"label": "left", "segment": [574.28, 579.28]}, "annotations_frame": {"label": "left", "segment": [14357.0, 14482.0]}, "annotations_rounded": {"label": "left", "segment": [574.0, 580.0]}, "duration": 5.0, "duration_frame": 125.0, "duration_rounded": 6.0, "subset": "train", "url": "https://www.youtube.com/watch?v=Y_tLNYQfjv0"}, "Y_tLNYQfjv0_10": {"annotations": {"label": "together", "segment": [651.64, 656.64]}, "annotations_frame": {"label": "together", "segment": [16291.0, 16416.0]}, "annotations_rounded": {"label": "together", "segment": [651.0, 657.0]}, "duration": 5.0, "duration_frame": 125.0, "duration_rounded": 6.0, "subset": "train", "url": "https://www.youtube.com/watch?v=Y_tLNYQfjv0"}, "Y_tLNYQfjv0_11": {"annotations": {"label": "together", "segment": [738.4, 743.4]}, "annotations_frame": {"label": "together", "segment": [18460.0, 18585.0]}, "annotations_rounded": {"label": "together", "segment": [738.0, 744.0]}, "duration": 5.0, "duration_frame": 125.0, "duration_rounded": 6.0, "subset": "train", "url": "https://www.youtube.com/watch?v=Y_tLNYQfjv0"}, "Y_tLNYQfjv0_12": {"annotations": {"label": "together", "segment": [931.44, 936.44]}, "annotations_frame": {"label": "together", "segment": [23286.0, 23411.0]}, "annotations_rounded": {"label": "together", "segment": [931.0, 937.0]}, "duration": 5.0, "duration_frame": 125.0, "duration_rounded": 6.0, "subset": "train", "url": "https://www.youtube.com/watch?v=Y_tLNYQfjv0"}}