{"ZRPxZGW-384_0": {"annotations": {"label": "left", "segment": [58.68, 63.68]}, "annotations_frame": {"label": "left", "segment": [1467.0, 1592.0]}, "annotations_rounded": {"label": "left", "segment": [58.0, 64.0]}, "duration": 5.0, "duration_frame": 125.0, "duration_rounded": 6.0, "subset": "train", "url": "https://www.youtube.com/watch?v=ZRPxZGW-384"}, "ZRPxZGW-384_1": {"annotations": {"label": "left", "segment": [70.0, 75.0]}, "annotations_frame": {"label": "left", "segment": [1750.0, 1875.0]}, "annotations_rounded": {"label": "left", "segment": [70.0, 75.0]}, "duration": 5.0, "duration_frame": 125.0, "duration_rounded": 5.0, "subset": "train", "url": "https://www.youtube.com/watch?v=ZRPxZGW-384"}, "ZRPxZGW-384_2": {"annotations": {"label": "right", "segment": [134.24, 139.24]}, "annotations_frame": {"label": "right", "segment": [3356.0, 3481.0]}, "annotations_rounded": {"label": "right", "segment": [134.0, 140.0]}, "duration": 5.0, "duration_frame": 125.0, "duration_rounded": 6.0, "subset": "train", "url": "https://www.youtube.com/watch?v=ZRPxZGW-384"}, "ZRPxZGW-384_3": {"annotations": {"label": "left", "segment": [199.44, 204.44]}, "annotations_frame": {"label": "left", "segment": [4986.0, 5111.0]}, "annotations_rounded": {"label": "left", "segment": [199.0, 205.0]}, "duration": 5.0, "duration_frame": 125.0, "duration_rounded": 6.0, "subset": "train", "url": "https://www.youtube.com/watch?v=ZRPxZGW-384"}, "ZRPxZGW-384_4": {"annotations": {"label": "together", "segment": [281.24, 286.24]}, "annotations_frame": {"label": "together", "segment": [7031.0, 7156.0]}, "annotations_rounded": {"label": "together", "segment": [281.0, 287.0]}, "duration": 5.0, "duration_frame": 125.0, "duration_rounded": 6.0, "subset": "train", "url": "https://www.youtube.com/watch?v=ZRPxZGW-384"}, "ZRPxZGW-384_5": {"annotations": {"label": "right", "segment": [414.08, 419.08]}, "annotations_frame": {"label": "right", "segment": [10352.0, 10477.0]}, "annotations_rounded": {"label": "right", "segment": [414.0, 420.0]}, "duration": 5.0, "duration_frame": 125.0, "duration_rounded": 6.0, "subset": "train", "url": "https://www.youtube.com/watch?v=ZRPxZGW-384"}, "ZRPxZGW-384_6": {"annotations": {"label": "left", "segment": [500.28, 505.28]}, "annotations_frame": {"label": "left", "segment": [12507.0, 12632.0]}, "annotations_rounded": {"label": "left", "segment": [500.0, 506.0]}, "duration": 5.0, "duration_frame": 125.0, "duration_rounded": 6.0, "subset": "train", "url": "https://www.youtube.com/watch?v=ZRPxZGW-384"}, "ZRPxZGW-384_7": {"annotations": {"label": "left", "segment": [646.24, 651.24]}, "annotations_frame": {"label": "left", "segment": [16156.0, 16281.0]}, "annotations_rounded": {"label": "left", "segment": [646.0, 652.0]}, "duration": 5.0, "duration_frame": 125.0, "duration_rounded": 6.0, "subset": "train", "url": "https://www.youtube.com/watch?v=ZRPxZGW-384"}, "ZRPxZGW-384_8": {"annotations": {"label": "right", "segment": [753.52, 758.52]}, "annotations_frame": {"label": "right", "segment": [18838.0, 18963.0]}, "annotations_rounded": {"label": "right", "segment": [753.0, 759.0]}, "duration": 5.0, "duration_frame": 125.0, "duration_rounded": 6.0, "subset": "train", "url": "https://www.youtube.com/watch?v=ZRPxZGW-384"}, "ZRPxZGW-384_9": {"annotations": {"label": "together", "segment": [845.6, 850.6]}, "annotations_frame": {"label": "together", "segment": [21140.0, 21265.0]}, "annotations_rounded": {"label": "together", "segment": [845.0, 851.0]}, "duration": 5.0, "duration_frame": 125.0, "duration_rounded": 6.0, "subset": "train", "url": "https://www.youtube.com/watch?v=ZRPxZGW-384"}, "ZRPxZGW-384_10": {"annotations": {"label": "right", "segment": [887.0, 892.0]}, "annotations_frame": {"label": "right", "segment": [22175.0, 22300.0]}, "annotations_rounded": {"label": "right", "segment": [887.0, 892.0]}, "duration": 5.0, "duration_frame": 125.0, "duration_rounded": 5.0, "subset": "train", "url": "https://www.youtube.com/watch?v=ZRPxZGW-384"}, "ZRPxZGW-384_11": {"annotations": {"label": "right", "segment": [935.0, 940.0]}, "annotations_frame": {"label": "right", "segment": [23375.0, 23500.0]}, "annotations_rounded": {"label": "right", "segment": [935.0, 940.0]}, "duration": 5.0, "duration_frame": 125.0, "duration_rounded": 5.0, "subset": "train", "url": "https://www.youtube.com/watch?v=ZRPxZGW-384"}, "ZRPxZGW-384_12": {"annotations": {"label": "right", "segment": [952.36, 957.36]}, "annotations_frame": {"label": "right", "segment": [23809.0, 23934.0]}, "annotations_rounded": {"label": "right", "segment": [952.0, 958.0]}, "duration": 5.0, "duration_frame": 125.0, "duration_rounded": 6.0, "subset": "train", "url": "https://www.youtube.com/watch?v=ZRPxZGW-384"}}